gitfucktime/__init__.py
gitfucktime/core.py
gitfucktime/main.py
gitfucktime/ui.py
gitfucktime/utils.py
gitfucktime-1.0.1.dist-info/licenses/LICENSE
gitfucktime-1.0.1.dist-info/METADATA
gitfucktime-1.0.1.dist-info/WHEEL
gitfucktime-1.0.1.dist-info/entry_points.txt
gitfucktime-1.0.1.dist-info/top_level.txt
gitfucktime-1.0.1.dist-info/RECORD
