Metadata-Version: 2.4
Name: gitfucktime
Version: 1.0.1
Summary: A CLI tool to rewrite git timestamps to standard work hours.
Author-email: G0razd <lukas.gorazd.hrodek@gmail.com>
Project-URL: Homepage, https://github.com/G0razd/gitfucktime
Project-URL: Bug Tracker, https://github.com/G0razd/gitfucktime/issues
Classifier: Programming Language :: Python :: 3
Classifier: License :: OSI Approved :: MIT License
Classifier: Operating System :: OS Independent
Requires-Python: >=3.7
License-File: LICENSE
Requires-Dist: rich
Requires-Dist: questionary
Dynamic: license-file
